{
  "timestamp": "2025-06-20T05:51:30.871Z",
  "mall": {
    "name": "광주김치몰 (K-Kimchi)",
    "url": "https://www.k-kimchi.kr/index.php",
    "region": "광주광역시",
    "mallId": "kkimchi",
    "status": "completed"
  },
  "analysis": {
    "structureAnalyzed": true,
    "productPagesIdentified": true,
    "categoryHierarchy": {
      "mainCategories": [
        "포기김치",
        "갓김치", 
        "깍두기",
        "묵은지",
        "특산김치"
      ],
      "urlPattern": "index.php?cate=[category_code]&type=view&num=[product_id]"
    }
  },
  "scraping": {
    "totalProductsFound": 120,
    "validProductsScraped": 104,
    "invalidProductsSkipped": 16,
    "scrapingSuccess": true,
    "dataQuality": {
      "withPrices": 104,
      "withImages": 104,
      "withUrls": 104,
      "withDescriptions": 38
    }
  },
  "registration": {
    "onlyFoodProducts": true,
    "individualProductsOnly": true,
    "noCategoriesRegistered": true,
    "productsRegistered": 104,
    "averagePrice": 17201,
    "priceRange": {
      "min": 6300,
      "max": 47880
    }
  },
  "verification": {
    "dataAccuracy": "verified",
    "allProductsValid": true,
    "noIssuesFound": true,
    "individualProductsConfirmed": true
  },
  "productBreakdown": {
    "categories": {
      "가공식품": 104
    },
    "kimchiTypes": {
      "포기김치/배추김치": 8,
      "갓김치": 14,
      "깍두기": 11,
      "묵은지": 3,
      "기타 특산김치": 68
    },
    "withQuantities": 36,
    "withBrandNames": 56,
    "withDiscounts": 99
  },
  "finalStatus": "✅ COMPLETED SUCCESSFULLY",
  "summary": "K-Kimchi shopping mall has been fully analyzed, scraped, and registered. All 104 valid food products (kimchi varieties) have been registered with complete data including titles, images, and prices. Each product is registered individually (no categories). Data quality is excellent with 100% coverage for essential fields."
}