{
  "timestamp": "2025-06-19T11:57:15.988Z",
  "mall": {
    "mallId": "chamds",
    "mallName": "참달성",
    "mallUrl": "https://chamds.com",
    "region": "경상북도"
  },
  "scraping": {
    "totalScraped": 22,
    "uniqueProducts": 18,
    "duplicatesRemoved": 4,
    "skipped": 0,
    "registered": 18
  },
  "products": {
    "added": 18,
    "totalInDatabase": 109,
    "chamdsProductsOnly": 18
  },
  "categories": {
    "distribution": {
      "가공식품": 18
    }
  },
  "dataQuality": {
    "withPrices": 18,
    "withoutPrices": 0,
    "withImages": 18,
    "averagePrice": 23861
  },
  "sampleProducts": [
    {
      "id": "chamds-108",
      "name": "농부 이학조의 생강진액 1병",
      "price": 30000,
      "category": "가공식품",
      "hasImage": true,
      "hasUrl": true
    },
    {
      "id": "chamds-109",
      "name": "농부 이학조의 생강진액 2병",
      "price": 60000,
      "category": "가공식품",
      "hasImage": true,
      "hasUrl": true
    },
    {
      "id": "chamds-118",
      "name": "행원정 등겨장 500g",
      "price": 12000,
      "category": "가공식품",
      "hasImage": true,
      "hasUrl": true
    },
    {
      "id": "chamds-119",
      "name": "행원정 들기름 240ml 선물세트 냉압착 들깨기름",
      "price": 40000,
      "category": "가공식품",
      "hasImage": true,
      "hasUrl": true
    },
    {
      "id": "chamds-120",
      "name": "행원정 정월된장 500g / 1kg",
      "price": 12000,
      "category": "가공식품",
      "hasImage": true,
      "hasUrl": true
    },
    {
      "id": "chamds-121",
      "name": "행원정 청국장 분말가루",
      "price": 22000,
      "category": "가공식품",
      "hasImage": true,
      "hasUrl": true
    },
    {
      "id": "chamds-122",
      "name": "행원정 청국장 분말스틱",
      "price": 8000,
      "category": "가공식품",
      "hasImage": true,
      "hasUrl": true
    },
    {
      "id": "chamds-15",
      "name": "미드미누룽지 1박스(280g x 16개)",
      "price": 55000,
      "category": "가공식품",
      "hasImage": true,
      "hasUrl": true
    },
    {
      "id": "chamds-16",
      "name": "미드미누룽지 800g /참달성",
      "price": 10000,
      "category": "가공식품",
      "hasImage": true,
      "hasUrl": true
    },
    {
      "id": "chamds-19",
      "name": "여주티백차",
      "price": 10000,
      "category": "가공식품",
      "hasImage": true,
      "hasUrl": true
    }
  ]
}