{
  "timestamp": "2025-06-21T12:54:54.054Z",
  "mallName": "강릉몰",
  "mallId": "gangneung",
  "totalProcessed": 25,
  "successfullyRegistered": 25,
  "skipped": 0,
  "totalProducts": 737,
  "categories": [
    "반려동물용품",
    "전통한과",
    "전통발효식품",
    "커피/음료",
    "수산물/건어물"
  ],
  "priceRange": {
    "min": 7900,
    "max": 60000,
    "average": 25612
  },
  "sampleProducts": [
    {
      "title": "락토펫 반려묘 프로바이오틱스 - 프리바이오틱스, 포스트바이오틱스 함유",
      "price": 10000,
      "category": "반려동물용품",
      "tags": [
        "반려동물",
        "강아지",
        "반려견",
        "펫",
        "영양제"
      ]
    },
    {
      "title": "락토펫 반려견 프로바이오틱스 - 프리바이오틱스, 포스트바이오틱스 함유",
      "price": 10000,
      "category": "반려동물용품",
      "tags": [
        "반려동물",
        "강아지",
        "반려견",
        "펫",
        "영양제"
      ]
    },
    {
      "title": "챔프로 시츄 전용 강아지 영양제 1~3단계 맞춤형",
      "price": 25000,
      "category": "반려동물용품",
      "tags": [
        "반려동물",
        "강아지",
        "반려견",
        "펫",
        "영양제"
      ]
    },
    {
      "title": "챔프로 요크셔테리어 전용 강아지 영양제 1~3단계 맞춤형",
      "price": 25000,
      "category": "반려동물용품",
      "tags": [
        "반려동물",
        "강아지",
        "반려견",
        "펫",
        "영양제"
      ]
    },
    {
      "title": "챔프로 스피츠 전용 강아지 영양제 1~3단계 맞춤형",
      "price": 25000,
      "category": "반려동물용품",
      "tags": [
        "반려동물",
        "강아지",
        "반려견",
        "펫",
        "영양제"
      ]
    }
  ]
}